pyster/__init__.py
pyster/__main__.py
pyster/common.py
pyster/gen/__init__.py
pyster/gen/__main__.py
pyster/gen/covDrivenFilter.py
pyster/gen/genRandomArg.py
pyster/gen/testFileGenerator.py
pyster/gen/testRunner.py
pyster/init/__init__.py
pyster/init/__main__.py
pyster/init/runtimeParse.py
pyster/init/staticParse.py
tests/__init__.py
tests/test_gen_stage.py
tests/test_init_stage.py
pyster_python-0.1.0.dist-info/LICENSE
pyster_python-0.1.0.dist-info/METADATA
pyster_python-0.1.0.dist-info/WHEEL
pyster_python-0.1.0.dist-info/top_level.txt
pyster_python-0.1.0.dist-info/RECORD
