Metadata-Version: 2.1
Name: pyster-python
Version: 0.1.0
Summary: Coverage-driven automatic unit test generator for Python projects.
Home-page: https://github.com/WenhaoSu/pyster
Author: Wenhao Su, Zhen Yu
Author-email: wenhaos3@illinois.edu
License: UNKNOWN
Platform: UNKNOWN
Classifier: Programming Language :: Python :: 3
Classifier: License :: OSI Approved :: MIT License
Classifier: Operating System :: OS Independent
Requires-Python: >=3.6
